
    {
        "BlockList" : {
            "url" : "URL",
            "word" : "Word"
        },
        "BlockPage" : {
            "root_default" : "You are accessing the Block page",
            "root_website" : "blocked website : ",
            "root_focus" : "blocked all website in focus mode ",
            "reason_focus" : "Focus mode has activated",
            "reason_website" : "blocked reason: accessed blocked url ",
            "reason_word": "blocked reason: it is contain restricted word ",
            "title" : "BLOCKED PAGE",
            "message" : "What are you doing in here? Get out !!",
            "visit_github_page" : "Visit github page:"
        },
        "Home" : {
            "main_tab" : "Home",
            "block_list_tab" : "Block List",
            "white_list_tab" : "White List",
            "focus_mode_tab" : "Focus Mode"
        },
        "Header" : {
            "status_on" : "ON",
            "status_off" : "OFF"
        },
        "InputTime" : {
            "days" : "Days",
            "hours" : "Hours",
            "minutes" : "Minutes",
            "seconds" : "Seconds",
            "focus_button_text" : "Set Focus Timer",
            "focus_mode_text" : "Focus Mode is Activated !",
            "reset_button_text" : "Reset Focus Timer",
            "set_time_error" : "Please set time more than 0 seconds"
        },
        "List" : {
            "remove" : "Remove"
        },
        "Main" : {
            "block_button_text" : "Block this site",
            "page_block" : "Are you want to block this site?",
            "page_blocked_cant" : "Can't block this page",
            "page_blocked" : "This page is blocked"
            
        },
        "Timer" : {
            "days" : "Days",
            "hours" : "Hours",
            "minutes" : "Minutes",
            "status_on" : "Focus Mode is On !",
            "seconds" : "Seconds"
        },
        "UrlList" : {
            "url_add" : "URL added : ",
            "url_add_error" : "It is Not an URL, Try it With Another URL",
            "url_added" : "is already added "
        },
        "WordList" : {
            "word_add" : "Word added : ",
            "word_add_error" : "Not a word",
            "word_add_short" : "Please input 3 or more characters",
            "word_added" : "is already added "
        },
        "WhiteList" : {
            "about" : "If you wish to access the website even it has restricted words you can fill it in here",
            "url_add" : "White List URL added : ",
            "url_add_error" : "It is Not an URL, Try it With Another URL",
            "url_add_error_block" : "Please delete the url from blocked site first",
            "url_added" : "is already added to White List"
        }
    }
